purkinje_uv/__init__.py
purkinje_uv/branch.py
purkinje_uv/config.py
purkinje_uv/edge.py
purkinje_uv/fractal_tree.py
purkinje_uv/fractal_tree_parameters.py
purkinje_uv/mesh.py
purkinje_uv/nodes.py
purkinje_uv/purkinje_tree.py
purkinje_uv-0.4.0.dist-info/licenses/LICENSE
utils/__init__.py
utils/igb_reader.py
utils/paraview_writer.py
utils/vtkutils.py
purkinje_uv-0.4.0.dist-info/METADATA
purkinje_uv-0.4.0.dist-info/WHEEL
purkinje_uv-0.4.0.dist-info/top_level.txt
purkinje_uv-0.4.0.dist-info/RECORD
