Metadata-Version: 2.4
Name: purkinje-uv
Version: 0.4.0
Summary: Utilities to generate Purkinje networks from fractal trees and mesh surfaces
Author-email: Ricardo García Ramírez <rgr.5882@gmail.com>
License-Expression: MIT
Project-URL: Homepage, https://github.com/ricardogr07/purkinje-uv/
Project-URL: Repository, https://github.com/ricardogr07/purkinje-uv/
Requires-Python: >=3.8
License-File: LICENSE
Requires-Dist: numpy
Requires-Dist: scipy
Requires-Dist: vtk
Requires-Dist: pyvista
Requires-Dist: meshio
Requires-Dist: fim-python
Provides-Extra: docs
Requires-Dist: sphinx<9,>=8; extra == "docs"
Requires-Dist: furo; extra == "docs"
Requires-Dist: sphinxcontrib-mermaid; extra == "docs"
Requires-Dist: sphinxcontrib-bibtex>=2.6; extra == "docs"
Requires-Dist: sphinx-multiversion>=0.2.4; extra == "docs"
Requires-Dist: nbsphinx>=0.9.5; extra == "docs"
Requires-Dist: nbconvert>=7.16; extra == "docs"
Requires-Dist: nbformat>=5.10; extra == "docs"
Requires-Dist: jupyter-client>=8.6; extra == "docs"
Requires-Dist: sphinx-copybutton>=0.5.2; extra == "docs"
Requires-Dist: sphinx-design>=0.6.0; extra == "docs"
Requires-Dist: nbsphinx-link>=1.3.1; extra == "docs"
Provides-Extra: dev
Requires-Dist: pytest; extra == "dev"
Requires-Dist: pytest-cov; extra == "dev"
Requires-Dist: ruff; extra == "dev"
Requires-Dist: mypy; extra == "dev"
Requires-Dist: pre-commit; extra == "dev"
Requires-Dist: meshio>=5.3; extra == "dev"
Provides-Extra: e2e
Requires-Dist: meshio>=5.3; extra == "e2e"
Requires-Dist: pyvista>=0.43; extra == "e2e"
Requires-Dist: pyvistaqt>=0.11; extra == "e2e"
Provides-Extra: gpu
Requires-Dist: cupy-cuda12x; platform_system == "Linux" and extra == "gpu"
Provides-Extra: all
Requires-Dist: sphinx<9,>=8; extra == "all"
Requires-Dist: furo; extra == "all"
Requires-Dist: sphinxcontrib-mermaid; extra == "all"
Requires-Dist: sphinxcontrib-bibtex>=2.6; extra == "all"
Requires-Dist: sphinx-multiversion>=0.2.4; extra == "all"
Requires-Dist: nbsphinx>=0.9.5; extra == "all"
Requires-Dist: nbconvert>=7.16; extra == "all"
Requires-Dist: nbformat>=5.10; extra == "all"
Requires-Dist: jupyter-client>=8.6; extra == "all"
Requires-Dist: sphinx-copybutton>=0.5.2; extra == "all"
Requires-Dist: sphinx-design>=0.6.0; extra == "all"
Requires-Dist: nbsphinx-link>=1.3.1; extra == "all"
Requires-Dist: pytest; extra == "all"
Requires-Dist: pytest-cov; extra == "all"
Requires-Dist: ruff; extra == "all"
Requires-Dist: mypy; extra == "all"
Requires-Dist: pre-commit; extra == "all"
Requires-Dist: meshio>=5.3; extra == "all"
Requires-Dist: pyvista>=0.43; extra == "all"
Requires-Dist: pyvistaqt>=0.11; extra == "all"
Dynamic: license-file
